biobookshelf/__init__.py
biobookshelf/__main__.py
biobookshelf/BA/__init__.py
biobookshelf/BA/bitarray_utils.py
biobookshelf/CLI/__init__.py
biobookshelf/CLI/unclassified_programs.py
biobookshelf/INT/__init__.py
biobookshelf/INT/integer.py
biobookshelf/IT/__init__.py
biobookshelf/IT/interval_tree_utils.py
biobookshelf/L/__init__.py
biobookshelf/L/l_functions.py
biobookshelf/MAP/__init__.py
biobookshelf/MAP/mapping.py
biobookshelf/MNG/__init__.py
biobookshelf/MNG/managers.py
biobookshelf/MP/__init__.py
biobookshelf/MP/multiprocessing_utils.py
biobookshelf/ONT/__init__.py
biobookshelf/ONT/nanopore_functions.py
biobookshelf/PD/__init__.py
biobookshelf/PD/pd_functions.py
biobookshelf/PDB/__init__.py
biobookshelf/PDB/pdb.py
biobookshelf/PKG/__init__.py
biobookshelf/PKG/package_util.py
biobookshelf/RNA/__init__.py
biobookshelf/RNA/rnaseq.py
biobookshelf/SAM/__init__.py
biobookshelf/SAM/sam_util.py
biobookshelf/SC/__init__.py
biobookshelf/SC/single_cell.py
biobookshelf/SEQ/__init__.py
biobookshelf/SEQ/sequence.py
biobookshelf/STR/__init__.py
biobookshelf/STR/string.py
biobookshelf/UniProt/__init__.py
biobookshelf/UniProt/uniprot.py
biobookshelf/WEB/__init__.py
biobookshelf/WEB/web_application.py
biobookshelf/ZA/__init__.py
biobookshelf/ZA/zarr_utils.py
biobookshelf/main/__init__.py
biobookshelf/main/unclassified_functions.py
biobookshelf-0.3.2.dist-info/.ipynb_checkpoints/entry_points-checkpoint.txt
biobookshelf-0.3.2.dist-info/LICENSE
biobookshelf-0.3.2.dist-info/METADATA
biobookshelf-0.3.2.dist-info/WHEEL
biobookshelf-0.3.2.dist-info/entry_points.txt
biobookshelf-0.3.2.dist-info/top_level.txt
biobookshelf-0.3.2.dist-info/RECORD
